sparkipy/__init__.py
sparkipy/runner.py
sparkipy/jobs/HelloWorldJob.py
sparkipy/jobs/PiJob.py
sparkipy/jobs/__init__.py
sparkipy/jobs/ajob.py
sparkipy/readers/__init__.py
sparkipy/readers/areader.py
sparkipy/readers/aws/__init__.py
sparkipy/readers/azure/__init__.py
sparkipy/readers/gcp/__init__.py
sparkipy/readers/gcp/big_query_reader.py
sparkipy/readers/gcp/google_cloud_storage_reader.py
sparkipy/transformers/__init__.py
sparkipy/utils/__init__.py
sparkipy/utils/utils.py
sparkipy/writers/__init__.py
sparkipy/writers/awriter.py
sparkipy/writers/aws/__init__.py
sparkipy/writers/azure/__init__.py
sparkipy/writers/gcp/__init__.py
sparkipy/writers/gcp/big_query_writer.py
tests/__init__.py
sparkipy-0.0.11.dist-info/LICENSE
sparkipy-0.0.11.dist-info/METADATA
sparkipy-0.0.11.dist-info/WHEEL
sparkipy-0.0.11.dist-info/top_level.txt
sparkipy-0.0.11.dist-info/RECORD
